{"duration": 823.0599110126495, "input_args": {"imgs": "<nibabel.nifti1.Nifti1Image object at 0x2b35db50b450>", "extraction_function": "<nilearn.input_data.nifti_labels_masker._ExtractionFunctor object at 0x2b35db8b8950>", "parameters": "{'background_label': 0, 'detrend': False, 'dtype': None, 'high_pass': None, 'high_variance_confounds': False, 'labels': None, 'labels_img': <nibabel.nifti1.Nifti1Image object at 0x2b35d8ca1250>, 'low_pass': None, 'mask_img': None, 'reports': True, 'smoothing_fwhm': None, 'standardize': True, 'standardize_confounds': True, 'strategy': 'mean', 't_r': None, 'target_shape': (147, 143, 221), 'target_affine': array([[-3.33330005e-01,  0.00000000e+00,  2.48350251e-09,\n         1.60015678e+00],\n       [ 0.00000000e+00, -3.88047178e-10,  3.33329946e-01,\n        -2.83515759e+01],\n       [ 0.00000000e+00, -3.33329946e-01, -6.98484826e-10,\n         2.05534554e+01],\n       [ 0.00000000e+00,  0.00000000e+00,  0.00000000e+00,\n         1.00000000e+00]])}", "confounds": "None", "sample_mask": "None", "copy": "True", "dtype": "None"}}